dataauto/__init__.py
dataauto/analysis_backup.py
dataauto/cli.py
dataauto/dashboard.py
dataauto/data_cleaner.py
dataauto/data_loader.py
dataauto/data_plotter.py
dataauto/data_saver.py
dataauto/model_trainer.py
dataauto/preprocessing.py
dataauto/report_generator.py
dataauto/scheduler.py
dataauto/utils.py
tests/__init__.py
tests/test_cli.py
tests/test_data_cleaner.py
tests/test_data_loader.py
tests/test_data_plotter.py
tests/test_model_trainer.py
tests/test_report_generator.py
tests/test_scheduler.py
tests/test_utils.py
dataauto-1.0.3.dist-info/LICENSE
dataauto-1.0.3.dist-info/METADATA
dataauto-1.0.3.dist-info/WHEEL
dataauto-1.0.3.dist-info/entry_points.txt
dataauto-1.0.3.dist-info/top_level.txt
dataauto-1.0.3.dist-info/RECORD
