Metadata-Version: 2.1
Name: dataauto
Version: 1.0.3
Summary: An open-source tool for automating data analysis tasks.
Home-page: https://github.com/r4mp4g3r/dataauto
Author: Pachigulla Ramtej
Author-email: ram.pachi.tej@example.com
Classifier: Programming Language :: Python :: 3
Classifier: License :: OSI Approved :: MIT License
Classifier: Operating System :: OS Independent
Requires-Python: >=3.6
License-File: LICENSE
Requires-Dist: click >=8.1.3
Requires-Dist: pandas >=1.5.3
Requires-Dist: numpy >=1.25.0
Requires-Dist: matplotlib >=3.7.1
Requires-Dist: seaborn >=0.12.2
